conf_ini_g/__init__.py
conf_ini_g/version.py
conf_ini_g/api/console.py
conf_ini_g/api/functional.py
conf_ini_g/api/storage.py
conf_ini_g/api/visual.py
conf_ini_g/catalog/boolean.py
conf_ini_g/catalog/callable.py
conf_ini_g/catalog/choices.py
conf_ini_g/catalog/collection.py
conf_ini_g/catalog/multitype.py
conf_ini_g/catalog/none.py
conf_ini_g/catalog/path.py
conf_ini_g/catalog/text_line.py
conf_ini_g/constant/console.py
conf_ini_g/constant/parameter.py
conf_ini_g/constant/section.py
conf_ini_g/constant/translator.py
conf_ini_g/constant/window.py
conf_ini_g/extension/path.py
conf_ini_g/extension/python.py
conf_ini_g/extension/string.py
conf_ini_g/interface/console/config.py
conf_ini_g/interface/storage/config.py
conf_ini_g/interface/window/config/action.py
conf_ini_g/interface/window/config/advanced.py
conf_ini_g/interface/window/config/main.py
conf_ini_g/interface/window/config/title.py
conf_ini_g/interface/window/parameter/main.py
conf_ini_g/interface/window/parameter/type.py
conf_ini_g/interface/window/parameter/value.py
conf_ini_g/interface/window/section/collection.py
conf_ini_g/interface/window/section/main.py
conf_ini_g/task/conversion.py
conf_ini_g/task/formatting.py
conf_ini_g/task/translation.py
conf_ini_g/type/config.py
conf_ini_g/type/dict.py
conf_ini_g/type/parameter.py
conf_ini_g/type/property.py
conf_ini_g/type/section.py
conf_ini_g-2025.7.dist-info/METADATA
conf_ini_g-2025.7.dist-info/WHEEL
conf_ini_g-2025.7.dist-info/top_level.txt
conf_ini_g-2025.7.dist-info/RECORD
