Metadata-Version: 2.4
Name: conf-ini-g
Version: 2025.7
Summary: App Configuration in INI format with Automatic Command-Line Parser and Graphical Interface Generation
Home-page: https://src.koda.cnrs.fr/eric.debreuve/conf-ini-g/
Author: Eric Debreuve
Author-email: eric.debreuve@cnrs.fr
License: CeCILL-2.1
Project-URL: Documentation, https://src.koda.cnrs.fr/eric.debreuve/conf-ini-g/-/wikis/home
Project-URL: Source, https://src.koda.cnrs.fr/eric.debreuve/conf-ini-g/
Keywords: app,application,configuration,INI,command-line,graphical interface
Classifier: Topic :: Software Development
Classifier: Intended Audience :: Developers
Classifier: License :: OSI Approved :: CEA CNRS Inria Logiciel Libre License, version 2.1 (CeCILL-2.1)
Classifier: Programming Language :: Python :: 3
Classifier: Development Status :: 4 - Beta
Requires-Python: >=3.11
Requires-Dist: babelwidget
Requires-Dist: logger-36
Requires-Dist: rich
Requires-Dist: scipy
Requires-Dist: value-factory
Dynamic: author
Dynamic: author-email
Dynamic: classifier
Dynamic: description
Dynamic: description-content-type
Dynamic: home-page
Dynamic: keywords
Dynamic: license
Dynamic: project-url
Dynamic: requires-dist
Dynamic: requires-python
Dynamic: summary
